{"id":88,"name":"Lê Thánh Tông","born":"25 tháng 8 năm 1442 Chùa Huy Văn","died":"3 tháng 3 năm 1497 (54 tuổi) Điện Bảo Quang, Đông Kinh","workTime":"26 tháng 6 năm 1460 - 3 tháng 3 năm 1497 (36 năm, 250 ngày)","era":{"Nhà Hậu Lê – giai đoạn Lê sơ":19},"father":{"Lê Thái Tông":85},"mother":{"Ngô Thị Ngọc Dao":702},"precededBy":{"Lê Hiến Tông":89},"succeededBy":{"Lê Nghi Dân":494},"relatedEvent":{"biên soạn Luật Hồng Đức":122},"relatedSite":{"Núi Lam Thành":652,"Đền thờ Trạng Trình Nguyễn Bỉnh Khiêm (thuộc Khu di tích Trạng Trình Nguyễn Bỉnh Khiêm)":370,"Thành cổ Hà Nội (KDT Hoàng thành Thăng Long)":546,"Đình Trà Cổ":143,"Cụm di tích và danh thắng núi Bài Thơ - Chùa Long Tiên - Đền Đức Ông":138,"Đền Cờn":716,"KDT Hoàng thành Thăng Long":544,"Đền Côn Giang, Từ đường họ Quách, Nhà thờ Quách Đình Bảo, Quách Hữu Nghiêm":398,"Chùa Hà":576,"Vịnh Hạ Long":139,"Khu khảo cổ 18 Hoàng Diệu (KDT Hoàng thành Thăng Long)":545,"Rú Thành (Núi Lam Thành)":707,"Chùa Bà Nành":601,"Đền Quán Thánh":548,"Đền thờ Trạng nguyên Phạm Đôn Lễ":391,"Hải Vân Quan":831,"Khu di tích Phố Hiến":532,"Động Kính Chủ":241,"Nhà thờ tổ thợ bạc (Lệ Châu hội quán)":1018,"Đền thờ Cao Lỗ":692,"Đền thờ Ngô Thị Ngọc Dao":727,"Đình Ngoại Bình Đà":621,"Ngũ Hành Sơn":819,"Khu lưu niệm Ngô Quang Bích":403,"Khu di tích Lam Kinh":643,"Văn Miếu - Quốc Tử Giám, Bia tiến sĩ Văn Miếu Thăng Long":604,"Công Thần Miếu Vĩnh Long":1101,"Đền thờ Nguyễn Xí":680,"Đền thờ Trần Nguyên Hãn":290,"Núi Đá Bia":874}}