{"id":786,"name":"Mộ Trần Văn Kỷ","location":"Phong Bình, Phong Điền","constructionDate":"N/A","note":"N/A","category":"Lịch sử","approved":"1995","relatedFigure":{"Tây Sơn":null,"Vũ Văn Nhậm":1522,"Ngô Thì Nhậm":703,"Lê Hiển Tông":126,"Phan Huy Ích":1172,"Nguyễn Huệ":801,"Trần Quang Diệu":1300,"Nguyễn Huy Tự":null,"Nguyễn Nghiễm":860,"Nguyễn Huy Oánh":null,"Nguyễn Phúc Ánh":null,"Ngô Văn Sở":708,"Nguyễn Nhạc":864,"Nguyễn Hữu Chỉnh":807,"Cảnh Hưng":null,"Nguyễn Thiếp":954,"Cảnh Thịnh":null,"Bùi Đắc Tuyên":175}}