{"id":895,"name":"Trường Dục Thanh","location":"Đức Nghĩa, Phan Thiết","constructionDate":"N/A","note":"N/A","category":"Lịch sử văn hóa","approved":"1986","relatedFigure":{"Phan Thiết":null,"Nguyễn Trọng Lội":null,"Hồ Tá Bang":null,"Nguyễn Hiệt Chi":null,"Ngô Văn Nhượng":null,"Sài Gòn":null,"Trần Quý Cáp":1223,"Nguyễn Tất Thành":812,"Phan Châu Trinh":1059,"Trương Gia Mô":null,"Nguyễn Thông":851,"Trần Lệ Chất":null,"Nguyễn Kinh Chi":null,"Hồ Chí Minh":170,"Bình Thuận":null,"Nguyễn Quý Anh":null,"Phan Bội Châu":1058,"Huỳnh Thúc Kháng":253,"Nguyễn Sinh Sắc":806}}